interpretr/__init__.py
interpretr-0.0.1.dist-info/METADATA
interpretr-0.0.1.dist-info/WHEEL
interpretr-0.0.1.dist-info/licenses/LICENSE
interpretr-0.0.1.dist-info/RECORD
